README.md
setup.py
kube_shodan.egg-info/PKG-INFO
kube_shodan.egg-info/SOURCES.txt
kube_shodan.egg-info/dependency_links.txt
kube_shodan.egg-info/entry_points.txt
kube_shodan.egg-info/requires.txt
kube_shodan.egg-info/top_level.txt
kubeshodan/__init__.py
kubeshodan/main.py