Metadata-Version: 2.1
Name: kube-shodan
Version: 0.0.2
Summary: kube-shodan registers all public IPs of a Kubernetes cluster to monitor.shodan.io.
Home-page: https://github.com/ekeih/kube-shodan
Author: Max Rosin
Author-email: kube-shodan@hackrid.de
License: GPL
Platform: UNKNOWN
Classifier: Programming Language :: Python :: 3
Requires-Python: >=3.7
